{
    "factories": [
        {
            "factoryName": "Becode Anvers",
            "factoryId": 92,
            "regionId": 29,
            "regionName": "Anvers",
            "countryId": 18,
            "countryName": "Belgique",
            "address": "Anvers",
            "city": null,
            "departement": "20",
            "postCode": "2000",
            "countryCode": "be",
            "lat": 51.2211,
            "lng": 4.39971,
            "btn_text": "En savoir plus",
            "btn_url": "https:\/\/www.becode.org\/",
            "partner": null
        },
        {
            "factoryName": "Becode Bruxelles",
            "factoryId": 89,
            "regionId": 26,
            "regionName": "Bruxelles",
            "countryId": 18,
            "countryName": "Belgique",
            "address": "Bruxelles",
            "city": null,
            "departement": "10",
            "postCode": "1000",
            "countryCode": "be",
            "lat": 50.8505,
            "lng": 4.34878,
            "btn_text": "En savoir plus",
            "btn_url": "https:\/\/www.becode.org\/",
            "partner": null
        },
        {
            "factoryName": "Becode Charleroi",
            "factoryId": 91,
            "regionId": 28,
            "regionName": "Charleroi",
            "countryId": 18,
            "countryName": "Belgique",
            "address": "Charleroi",
            "city": null,
            "departement": "60",
            "postCode": "6000",
            "countryCode": "be",
            "lat": 50.412,
            "lng": 4.44362,
            "btn_text": "En savoir plus",
            "btn_url": "https:\/\/www.becode.org\/",
            "partner": null
        },
        {
            "factoryName": "Becode Limburg",
            "factoryId": 90,
            "regionId": 27,
            "regionName": "Genk, Vlaanderen",
            "countryId": 18,
            "countryName": "Belgique",
            "address": "Genk",
            "city": null,
            "departement": "36",
            "postCode": "3600",
            "countryCode": "be",
            "lat": 50.9655,
            "lng": 5.50015,
            "btn_text": "En savoir plus",
            "btn_url": "https:\/\/www.becode.org\/",
            "partner": null
        },
        {
            "factoryName": "Becode Li\u00e8ge",
            "factoryId": 93,
            "regionId": 30,
            "regionName": "Li\u00e8ge",
            "countryId": 18,
            "countryName": "Belgique",
            "address": "Li\u00e8ge",
            "city": null,
            "departement": "40",
            "postCode": "4000",
            "countryCode": "be",
            "lat": 50.6451,
            "lng": 5.57342,
            "btn_text": "En savoir plus",
            "btn_url": "https:\/\/www.becode.org\/",
            "partner": null
        },
        {
            "factoryName": "Simplon AUF@ Ouagadougo",
            "factoryId": 180,
            "regionId": 45,
            "regionName": "Ouagadougou",
            "countryId": 233,
            "countryName": "Burkina Faso",
            "address": "Ouagadougou",
            "city": null,
            "departement": "01",
            "postCode": "01 BP 1773 OUAGADOUGOU 01",
            "countryCode": "bf",
            "lat": 12.3681,
            "lng": -1.52709,
            "btn_text": "En savoir plus",
            "btn_url": "https:\/\/burkina-faso.simplon.co\/",
            "partner": null
        },
        {
            "factoryName": "Simplon C\u00f4te d\u2019Ivoire",
            "factoryId": 84,
            "regionId": 22,
            "regionName": "Abidjan",
            "countryId": 110,
            "countryName": "C\u00f4te d'Ivoire",
            "address": "Abidjan",
            "city": null,
            "departement": "01",
            "postCode": "01 BP 10605 ABIDJAN 01",
            "countryCode": "ci",
            "lat": 5.32036,
            "lng": -4.01611,
            "btn_text": "En savoir plus",
            "btn_url": "https:\/\/www.facebook.com\/ReferentCoteDivoire\/",
            "partner": null
        },
        {
            "factoryName": "MTN ACADEMY & SIMPLON",
            "factoryId": 142,
            "regionId": 22,
            "regionName": "Abidjan",
            "countryId": 110,
            "countryName": "C\u00f4te d'Ivoire",
            "address": "Abidjan",
            "city": null,
            "departement": "01",
            "postCode": "01 BP 10605 ABIDJAN 01",
            "countryCode": "ci",
            "lat": 5.32036,
            "lng": -4.01611,
            "btn_text": "En savoir plus",
            "btn_url": "https:\/\/www.facebook.com\/ReferentCoteDivoire\/",
            "partner": null
        },
        {
            "factoryName": "Factor\u00eda F5",
            "factoryId": 94,
            "regionId": 31,
            "regionName": "Barcelone",
            "countryId": 203,
            "countryName": "Espagne",
            "address": "Barcelone",
            "city": null,
            "departement": "08",
            "postCode": "08001",
            "countryCode": "es",
            "lat": 41.3829,
            "lng": 2.17743,
            "btn_text": "En savoir plus",
            "btn_url": "http:\/\/www.factoriaf5.org\/",
            "partner": null
        },
        {
            "factoryName": "Factor\u00eda F5 - Bilbao",
            "factoryId": 178,
            "regionId": 43,
            "regionName": "Bilbao",
            "countryId": 203,
            "countryName": "Espagne",
            "address": "Bilbao",
            "city": null,
            "departement": "48",
            "postCode": "48001",
            "countryCode": "es",
            "lat": 43.2535,
            "lng": -2.93693,
            "btn_text": "En savoir plus",
            "btn_url": "http:\/\/www.factoriaf5.org\/",
            "partner": null
        },
        {
            "factoryName": "Factor\u00eda F5 Madrid",
            "factoryId": 177,
            "regionId": 42,
            "regionName": "Madrid",
            "countryId": 203,
            "countryName": "Espagne",
            "address": "Madrid",
            "city": null,
            "departement": "28",
            "postCode": "28001",
            "countryCode": "es",
            "lat": 40.4167,
            "lng": -3.70358,
            "btn_text": "En savoir plus",
            "btn_url": "http:\/\/www.factoriaf5.org\/",
            "partner": null
        },
        {
            "factoryName": "Simplon Clermont",
            "factoryId": 40,
            "regionId": 1,
            "regionName": "Auvergne-Rh\u00f4ne-Alpes",
            "countryId": 75,
            "countryName": "France",
            "address": "Clermont-Ferrand",
            "city": null,
            "departement": "63",
            "postCode": "63000",
            "countryCode": "fr",
            "lat": 45.7797,
            "lng": 3.08682,
            "btn_text": "En savoir plus",
            "btn_url": "https:\/\/auvergnerhonealpes.simplon.co\/clermont-ferrand.html",
            "partner": null
        },
        {
            "factoryName": "Simplon V'E Le Cheylard",
            "factoryId": 17,
            "regionId": 1,
            "regionName": "Auvergne-Rh\u00f4ne-Alpes",
            "countryId": 75,
            "countryName": "France",
            "address": "Le Cheylard",
            "city": null,
            "departement": "07",
            "postCode": "07160",
            "countryCode": "fr",
            "lat": 44.9062,
            "lng": 4.42406,
            "btn_text": "En savoir plus",
            "btn_url": "https:\/\/en-07.fr\/?fbclid=IwAR0YeLACRwcoqSsWdSvHRlxIbZF_FWo5-WzFvzD_1yY7MzolH5SwsW8AHb8",
            "partner": null
        },
        {
            "factoryName": "Simplon Roanne",
            "factoryId": 71,
            "regionId": 1,
            "regionName": "Auvergne-Rh\u00f4ne-Alpes",
            "countryId": 75,
            "countryName": "France",
            "address": "7 Place des Minimes",
            "city": "Roanne",
            "departement": "42",
            "postCode": "42300",
            "countryCode": "fr",
            "lat": 46.0352,
            "lng": 4.07577,
            "btn_text": "En savoir plus",
            "btn_url": "https:\/\/simplon-roanne.com\/",
            "partner": null
        },
        {
            "factoryName": "Simplon Moulin",
            "factoryId": 78,
            "regionId": 1,
            "regionName": "Auvergne-Rh\u00f4ne-Alpes",
            "countryId": 75,
            "countryName": "France",
            "address": "18 Rue des Tanneries",
            "city": "Moulins",
            "departement": "03",
            "postCode": "03000",
            "countryCode": "fr",
            "lat": 46.5661,
            "lng": 3.33777,
            "btn_text": "En savoir plus",
            "btn_url": "https:\/\/campusnumerique.auvergnerhonealpes.fr\/acteur\/face-territoire-bourbonnais\/",
            "partner": null
        },
        {
            "factoryName": "Simplon Saint-Etienne",
            "factoryId": 77,
            "regionId": 1,
            "regionName": "Auvergne-Rh\u00f4ne-Alpes",
            "countryId": 75,
            "countryName": "France",
            "address": "8 Rue Tarentaize",
            "city": "Saint-\u00c9tienne",
            "departement": "42",
            "postCode": "42000",
            "countryCode": "fr",
            "lat": 45.4374,
            "lng": 4.38167,
            "btn_text": "En savoir plus",
            "btn_url": "https:\/\/simplon-saint-etienne.com\/",
            "partner": "Garage 404"
        },
        {
            "factoryName": "Simplon Lyon",
            "factoryId": 105,
            "regionId": 1,
            "regionName": "Auvergne-Rh\u00f4ne-Alpes",
            "countryId": 75,
            "countryName": "France",
            "address": "34 Rue Antoine Primat",
            "city": "Villeurbanne",
            "departement": "69",
            "postCode": "69100",
            "countryCode": "fr",
            "lat": 45.7581,
            "lng": 4.8944,
            "btn_text": "En savoir plus",
            "btn_url": "https:\/\/auvergnerhonealpes.simplon.co\/lyon.html",
            "partner": null
        },
        {
            "factoryName": "Simplon Chamb\u00e9ry",
            "factoryId": 75,
            "regionId": 1,
            "regionName": "Auvergne-Rh\u00f4ne-Alpes",
            "countryId": 75,
            "countryName": "France",
            "address": "24 Avenue Daniel Rops",
            "city": "Chamb\u00e9ry",
            "departement": "73",
            "postCode": "73000",
            "countryCode": "fr",
            "lat": 45.6027,
            "lng": 5.91343,
            "btn_text": "En savoir plus",
            "btn_url": "https:\/\/auvergnerhonealpes.simplon.co\/chambery.html",
            "partner": null
        },
        {
            "factoryName": "Simplon Grenoble",
            "factoryId": 38,
            "regionId": 1,
            "regionName": "Auvergne-Rh\u00f4ne-Alpes",
            "countryId": 75,
            "countryName": "France",
            "address": "34 Avenue de l'Europe",
            "city": "Grenoble",
            "departement": "38",
            "postCode": "38100",
            "countryCode": "fr",
            "lat": 45.1594,
            "lng": 5.73471,
            "btn_text": "En savoir plus",
            "btn_url": "https:\/\/auvergnerhonealpes.simplon.co\/grenoble.html",
            "partner": null
        },
        {
            "factoryName": "Simplon Le Puy-en-Velay",
            "factoryId": 194,
            "regionId": 1,
            "regionName": "Auvergne-Rh\u00f4ne-Alpes",
            "countryId": 75,
            "countryName": "France",
            "address": "Rue du Pensionnat Notre-Dame de France",
            "city": "Le Puy-en-Velay",
            "departement": "43",
            "postCode": "43000",
            "countryCode": "fr",
            "lat": 45.0408,
            "lng": 3.87959,
            "btn_text": "En savoir plus",
            "btn_url": "https:\/\/www.campus26.com\/",
            "partner": "Campus 26"
        },
        {
            "factoryName": "GRETA 25",
            "factoryId": 275,
            "regionId": 3,
            "regionName": "Bourgogne-Franche-Comt\u00e9",
            "countryId": 75,
            "countryName": "France",
            "address": "35 Avenue de Montrapon",
            "city": "Besan\u00e7on",
            "departement": "25",
            "postCode": "25000",
            "countryCode": "fr",
            "lat": 47.2466,
            "lng": 6.00811,
            "btn_text": "",
            "btn_url": null,
            "partner": "GRETA"
        },
        {
            "factoryName": "GRETA 21",
            "factoryId": 274,
            "regionId": 3,
            "regionName": "Bourgogne-Franche-Comt\u00e9",
            "countryId": 75,
            "countryName": "France",
            "address": "20 Boulevard Voltaire",
            "city": "Dijon",
            "departement": "21",
            "postCode": "21000",
            "countryCode": "fr",
            "lat": 47.3176,
            "lng": 5.05157,
            "btn_text": "",
            "btn_url": null,
            "partner": "GRETA"
        },
        {
            "factoryName": "Data\u2019Lab \u2013 Simplon powered by GRETA Val de Loire",
            "factoryId": 62,
            "regionId": 4,
            "regionName": "Centre-Val de Loire",
            "countryId": 75,
            "countryName": "France",
            "address": "Tours",
            "city": null,
            "departement": "37",
            "postCode": "37000",
            "countryCode": "fr",
            "lat": 47.3927,
            "lng": 0.688266,
            "btn_text": "En savoir plus",
            "btn_url": "https:\/\/centrevaldeloire.simplon.co\/",
            "partner": null
        },
        {
            "factoryName": "Greta Val de Loire  - Simplon Tours",
            "factoryId": 220,
            "regionId": 4,
            "regionName": "Centre-Val de Loire",
            "countryId": 75,
            "countryName": "France",
            "address": "6 Avenue de S\u00e9vign\u00e9",
            "city": "Tours",
            "departement": "37",
            "postCode": "37200",
            "countryCode": "fr",
            "lat": 47.3595,
            "lng": 0.698462,
            "btn_text": "",
            "btn_url": null,
            "partner": null
        },
        {
            "factoryName": "Simplon.co - Nancy",
            "factoryId": 128,
            "regionId": 6,
            "regionName": "Grand Est",
            "countryId": 75,
            "countryName": "France",
            "address": "Nancy",
            "city": null,
            "departement": "54",
            "postCode": "54000",
            "countryCode": "fr",
            "lat": 48.6927,
            "lng": 6.18366,
            "btn_text": "En savoir plus",
            "btn_url": "https:\/\/grandest.simplon.co\/",
            "partner": "Microsoft"
        },
        {
            "factoryName": "ALAJI powered by Simplon",
            "factoryId": 28,
            "regionId": 6,
            "regionName": "Grand Est",
            "countryId": 75,
            "countryName": "France",
            "address": "12 Rue Thomas Edison",
            "city": "Metz",
            "departement": "57",
            "postCode": "57070",
            "countryCode": "fr",
            "lat": 49.103,
            "lng": 6.22583,
            "btn_text": "En savoir plus",
            "btn_url": "https:\/\/grandest.simplon.co\/",
            "partner": "ALAJI"
        },
        {
            "factoryName": "CFAI Champagne Ardenne (UIMM)",
            "factoryId": 73,
            "regionId": 6,
            "regionName": "Grand Est",
            "countryId": 75,
            "countryName": "France",
            "address": "Charleville-M\u00e9zi\u00e8res",
            "city": null,
            "departement": "08",
            "postCode": "08000",
            "countryCode": "fr",
            "lat": 49.7601,
            "lng": 4.71958,
            "btn_text": "En savoir plus",
            "btn_url": "https:\/\/www.poleformation-cci08.fr\/simplon-charleville\/",
            "partner": "CCI Ardennes"
        },
        {
            "factoryName": "IRFA EST x Simplon.co - Mulhouse",
            "factoryId": 120,
            "regionId": 6,
            "regionName": "Grand Est",
            "countryId": 75,
            "countryName": "France",
            "address": "61 All\u00e9e Gluck",
            "city": "Mulhouse",
            "departement": "68",
            "postCode": "68200",
            "countryCode": "fr",
            "lat": 47.7558,
            "lng": 7.32033,
            "btn_text": "En savoir plus",
            "btn_url": "https:\/\/grandest.simplon.co\/",
            "partner": "IRFA Est"
        },
        {
            "factoryName": "Simplon Reims",
            "factoryId": 173,
            "regionId": 6,
            "regionName": "Grand Est",
            "countryId": 75,
            "countryName": "France",
            "address": "Reims",
            "city": null,
            "departement": "51",
            "postCode": "51100",
            "countryCode": "fr",
            "lat": 49.2652,
            "lng": 4.02851,
            "btn_text": "En savoir plus",
            "btn_url": "https:\/\/grandest.simplon.co\/",
            "partner": null
        },
        {
            "factoryName": "Simplon Strasbourg",
            "factoryId": 158,
            "regionId": 6,
            "regionName": "Grand Est",
            "countryId": 75,
            "countryName": "France",
            "address": "21 Rue Jacobi-Netter",
            "city": "Strasbourg",
            "departement": "67",
            "postCode": "67200",
            "countryCode": "fr",
            "lat": 48.587,
            "lng": 7.7055,
            "btn_text": "En savoir plus",
            "btn_url": "https:\/\/grandest.simplon.co\/",
            "partner": null
        },
        {
            "factoryName": "Ecole IA Microsoft - Rennes",
            "factoryId": 185,
            "regionId": 17,
            "regionName": "Grand Ouest",
            "countryId": 75,
            "countryName": "France",
            "address": null,
            "city": null,
            "departement": null,
            "postCode": null,
            "countryCode": null,
            "lat": 48.1129544,
            "lng": -1.7126652,
            "btn_text": "En savoir plus",
            "btn_url": "https:\/\/grandouest.simplon.co\/",
            "partner": null
        },
        {
            "factoryName": "Simplon  Nantes",
            "factoryId": 184,
            "regionId": 17,
            "regionName": "Grand Ouest",
            "countryId": 75,
            "countryName": "France",
            "address": "50 Boulevard Albert Einstein",
            "city": "Nantes",
            "departement": "44",
            "postCode": "44300",
            "countryCode": "fr",
            "lat": 47.2614,
            "lng": -1.56418,
            "btn_text": "En savoir plus",
            "btn_url": "https:\/\/grandouest.simplon.co\/",
            "partner": null
        },
        {
            "factoryName": "Simplon Angers",
            "factoryId": 216,
            "regionId": 17,
            "regionName": "Grand Ouest",
            "countryId": 75,
            "countryName": "France",
            "address": "Angers",
            "city": null,
            "departement": "49",
            "postCode": "49000",
            "countryCode": "fr",
            "lat": 47.4738,
            "lng": -0.54774,
            "btn_text": "",
            "btn_url": null,
            "partner": null
        },
        {
            "factoryName": "Ecole IA Microsoft By Simplon - ISEN Caen",
            "factoryId": 248,
            "regionId": 17,
            "regionName": "Grand Ouest",
            "countryId": 75,
            "countryName": "France",
            "address": "Caen",
            "city": null,
            "departement": "14",
            "postCode": "14000",
            "countryCode": "fr",
            "lat": 49.1821,
            "lng": -0.370609,
            "btn_text": "",
            "btn_url": null,
            "partner": null
        },
        {
            "factoryName": "Ecole IA Microsoft French Tech Brest +",
            "factoryId": 174,
            "regionId": 17,
            "regionName": "Grand Ouest",
            "countryId": 75,
            "countryName": "France",
            "address": "Brest",
            "city": null,
            "departement": "29",
            "postCode": "29200",
            "countryCode": "fr",
            "lat": 48.3899,
            "lng": -4.48681,
            "btn_text": "En savoir plus",
            "btn_url": "https:\/\/grandouest.simplon.co\/",
            "partner": "ISEN"
        },
        {
            "factoryName": "Simplon Rennes",
            "factoryId": 155,
            "regionId": 17,
            "regionName": "Grand Ouest",
            "countryId": 75,
            "countryName": "France",
            "address": null,
            "city": null,
            "departement": null,
            "postCode": null,
            "countryCode": null,
            "lat": 48.1129544,
            "lng": -1.7126652,
            "btn_text": "En savoir plus",
            "btn_url": "https:\/\/grandouest.simplon.co",
            "partner": "Cr\u00e9dit Agricole d'Ille-et-Vilaine"
        },
        {
            "factoryName": "INSA Rouen Normandie powered by Simplon.co",
            "factoryId": 70,
            "regionId": 14,
            "regionName": "Haute-Normandie",
            "countryId": 75,
            "countryName": "France",
            "address": "Rouen",
            "city": null,
            "departement": "76",
            "postCode": "76000",
            "countryCode": "fr",
            "lat": 49.443,
            "lng": 1.10251,
            "btn_text": "En savoir plus",
            "btn_url": "https:\/\/normandie.simplon.co\/",
            "partner": "INSA Rouen"
        },
        {
            "factoryName": "Digifab Le Havre powered by Simplon",
            "factoryId": 63,
            "regionId": 14,
            "regionName": "Haute-Normandie",
            "countryId": 75,
            "countryName": "France",
            "address": "Le Havre",
            "city": null,
            "departement": "76",
            "postCode": "76600",
            "countryCode": "fr",
            "lat": 49.4943,
            "lng": 0.107984,
            "btn_text": "En savoir plus",
            "btn_url": "https:\/\/normandie.simplon.co\/",
            "partner": "Digifab"
        },
        {
            "factoryName": "Simplon B\u00e9thune",
            "factoryId": 126,
            "regionId": 9,
            "regionName": "Hauts-de-France",
            "countryId": 75,
            "countryName": "France",
            "address": "35 Boulevard Raymond Poincar\u00e9",
            "city": "B\u00e9thune",
            "departement": "62",
            "postCode": "62400",
            "countryCode": "fr",
            "lat": 50.5245,
            "lng": 2.64049,
            "btn_text": "En savoir plus",
            "btn_url": "https:\/\/hautsdefrance.simplon.co\/",
            "partner": null
        },
        {
            "factoryName": "Simplon Roubaix",
            "factoryId": 111,
            "regionId": 9,
            "regionName": "Hauts-de-France",
            "countryId": 75,
            "countryName": "France",
            "address": "Roubaix",
            "city": null,
            "departement": "59",
            "postCode": "59100",
            "countryCode": "fr",
            "lat": 50.6893,
            "lng": 3.18074,
            "btn_text": "En savoir plus",
            "btn_url": "https:\/\/hautsdefrance.simplon.co\/",
            "partner": null
        },
        {
            "factoryName": "Simplon Boulogne-sur-Mer",
            "factoryId": 47,
            "regionId": 9,
            "regionName": "Hauts-de-France",
            "countryId": 75,
            "countryName": "France",
            "address": "Boulogne-sur-Mer",
            "city": null,
            "departement": "62",
            "postCode": "62200",
            "countryCode": "fr",
            "lat": 50.7256,
            "lng": 1.61396,
            "btn_text": "En savoir plus",
            "btn_url": "https:\/\/hautsdefrance.simplon.co\/",
            "partner": null
        },
        {
            "factoryName": "Simplon Lille -Wazemmes",
            "factoryId": 246,
            "regionId": 9,
            "regionName": "Hauts-de-France",
            "countryId": 75,
            "countryName": "France",
            "address": "47 Rue Barth\u00e9l\u00e9my Delespaul",
            "city": "Lille",
            "departement": "59",
            "postCode": "59000",
            "countryCode": "fr",
            "lat": 50.6243,
            "lng": 3.06104,
            "btn_text": "",
            "btn_url": null,
            "partner": null
        },
        {
            "factoryName": "Simplon Arras",
            "factoryId": 209,
            "regionId": 9,
            "regionName": "Hauts-de-France",
            "countryId": 75,
            "countryName": "France",
            "address": "Arras",
            "city": null,
            "departement": "62",
            "postCode": "62000",
            "countryCode": "fr",
            "lat": 50.2891,
            "lng": 2.78004,
            "btn_text": "",
            "btn_url": null,
            "partner": null
        },
        {
            "factoryName": "100% \u00e0 distance",
            "factoryId": 252,
            "regionId": 9,
            "regionName": "Hauts-de-France",
            "countryId": 75,
            "countryName": "France",
            "address": "France",
            "city": null,
            "departement": null,
            "postCode": null,
            "countryCode": "fr",
            "lat": 46.2276,
            "lng": 2.21375,
            "btn_text": "",
            "btn_url": null,
            "partner": null
        },
        {
            "factoryName": "Simplon - Lens",
            "factoryId": 245,
            "regionId": 9,
            "regionName": "Hauts-de-France",
            "countryId": 75,
            "countryName": "France",
            "address": "72 Rue Casimir Beugnet",
            "city": "Lens",
            "departement": "62",
            "postCode": "62300",
            "countryCode": "fr",
            "lat": 50.4333,
            "lng": 2.8317,
            "btn_text": "",
            "btn_url": null,
            "partner": null
        },
        {
            "factoryName": "Simplon Calais",
            "factoryId": 60,
            "regionId": 9,
            "regionName": "Hauts-de-France",
            "countryId": 75,
            "countryName": "France",
            "address": "Calais",
            "city": null,
            "departement": "62",
            "postCode": "62100",
            "countryCode": "fr",
            "lat": 50.9475,
            "lng": 1.85566,
            "btn_text": "En savoir plus",
            "btn_url": "http:\/\/calais.simplon.co\/",
            "partner": null
        },
        {
            "factoryName": "Simplon Dunkerque",
            "factoryId": 254,
            "regionId": 9,
            "regionName": "Hauts-de-France",
            "countryId": 75,
            "countryName": "France",
            "address": "Dunkerque",
            "city": null,
            "departement": "59",
            "postCode": "59140",
            "countryCode": "fr",
            "lat": 51.033,
            "lng": 2.377,
            "btn_text": "",
            "btn_url": null,
            "partner": null
        },
        {
            "factoryName": "Simplon Valenciennes - Les Ateliers Num\u00e9riques",
            "factoryId": 207,
            "regionId": 9,
            "regionName": "Hauts-de-France",
            "countryId": 75,
            "countryName": "France",
            "address": "Valenciennes",
            "city": null,
            "departement": "59",
            "postCode": "59300",
            "countryCode": "fr",
            "lat": 50.3591,
            "lng": 3.52506,
            "btn_text": "",
            "btn_url": null,
            "partner": null
        },
        {
            "factoryName": "Simplon Lille - Euratechnologie",
            "factoryId": 157,
            "regionId": 9,
            "regionName": "Hauts-de-France",
            "countryId": 75,
            "countryName": "France",
            "address": "165 Avenue de Bretagne",
            "city": "Lille",
            "departement": "59",
            "postCode": "59000",
            "countryCode": "fr",
            "lat": 50.6351,
            "lng": 3.02334,
            "btn_text": "En savoir plus",
            "btn_url": "https:\/\/hautsdefrance.simplon.co\/",
            "partner": null
        },
        {
            "factoryName": "Massy",
            "factoryId": 251,
            "regionId": 10,
            "regionName": "\u00cele-de-France",
            "countryId": 75,
            "countryName": "France",
            "address": "Massy",
            "city": null,
            "departement": "91",
            "postCode": "91300",
            "countryCode": "fr",
            "lat": 48.7305,
            "lng": 2.2765,
            "btn_text": "",
            "btn_url": null,
            "partner": null
        },
        {
            "factoryName": "Simplon Nanterre",
            "factoryId": 45,
            "regionId": 10,
            "regionName": "\u00cele-de-France",
            "countryId": 75,
            "countryName": "France",
            "address": "26 Rue des Amandiers",
            "city": "Nanterre",
            "departement": "92",
            "postCode": "92000",
            "countryCode": "fr",
            "lat": 48.8901,
            "lng": 2.2035,
            "btn_text": "En savoir plus",
            "btn_url": "https:\/\/iledefrance.simplon.co\/je-candidate",
            "partner": null
        },
        {
            "factoryName": "La d\u00e9fense",
            "factoryId": 250,
            "regionId": 10,
            "regionName": "\u00cele-de-France",
            "countryId": 75,
            "countryName": "France",
            "address": "La D\u00e9fense",
            "city": "Courbevoie",
            "departement": "92",
            "postCode": "92800",
            "countryCode": "fr",
            "lat": 48.8904,
            "lng": 2.2403,
            "btn_text": "",
            "btn_url": null,
            "partner": null
        },
        {
            "factoryName": "Simplon Villetaneuse",
            "factoryId": 172,
            "regionId": 10,
            "regionName": "\u00cele-de-France",
            "countryId": 75,
            "countryName": "France",
            "address": "2 Rue de l'Universit\u00e9",
            "city": "Villetaneuse",
            "departement": "93",
            "postCode": "93430",
            "countryCode": "fr",
            "lat": 48.9582,
            "lng": 2.3419,
            "btn_text": "En savoir plus",
            "btn_url": "https:\/\/iledefrance.simplon.co\/je-candidate",
            "partner": null
        },
        {
            "factoryName": "Simplon Aulnay-sous-Bois",
            "factoryId": 9,
            "regionId": 10,
            "regionName": "\u00cele-de-France",
            "countryId": 75,
            "countryName": "France",
            "address": "1 Rue Auguste Renoir",
            "city": "Aulnay-sous-Bois",
            "departement": "93",
            "postCode": "93600",
            "countryCode": "fr",
            "lat": 48.9568,
            "lng": 2.49322,
            "btn_text": "En savoir plus",
            "btn_url": "https:\/\/iledefrance.simplon.co\/je-candidate",
            "partner": null
        },
        {
            "factoryName": "Simplon Torcy",
            "factoryId": 219,
            "regionId": 10,
            "regionName": "\u00cele-de-France",
            "countryId": 75,
            "countryName": "France",
            "address": "1 bis Promenade du Belv\u00e9d\u00e8re",
            "city": "Torcy",
            "departement": "77",
            "postCode": "77200",
            "countryCode": "fr",
            "lat": 48.8407,
            "lng": 2.65337,
            "btn_text": "En savoir plus",
            "btn_url": "https:\/\/iledefrance.simplon.co\/je-candidate",
            "partner": null
        },
        {
            "factoryName": "Simplon Paris 20",
            "factoryId": 32,
            "regionId": 10,
            "regionName": "\u00cele-de-France",
            "countryId": 75,
            "countryName": "France",
            "address": "4 Rue Serpollet",
            "city": "Paris 20e Arrondissement",
            "departement": "75",
            "postCode": "75020",
            "countryCode": "fr",
            "lat": 48.8608,
            "lng": 2.412,
            "btn_text": "En savoir plus",
            "btn_url": "https:\/\/iledefrance.simplon.co\/je-candidate",
            "partner": null
        },
        {
            "factoryName": "Simplon Paris 09 - Platform 58",
            "factoryId": 26,
            "regionId": 10,
            "regionName": "\u00cele-de-France",
            "countryId": 75,
            "countryName": "France",
            "address": "58 Rue de la Victoire",
            "city": "Paris 9e Arrondissement",
            "departement": "75",
            "postCode": "75009",
            "countryCode": "fr",
            "lat": 48.8752,
            "lng": 2.33536,
            "btn_text": "En savoir plus",
            "btn_url": "https:\/\/www.platform58.fr\/",
            "partner": "La Banque Postale"
        },
        {
            "factoryName": "Simplon Montreuil",
            "factoryId": 23,
            "regionId": 10,
            "regionName": "\u00cele-de-France",
            "countryId": 75,
            "countryName": "France",
            "address": "14 Rue de la Beaune",
            "city": "Montreuil",
            "departement": "93",
            "postCode": "93100",
            "countryCode": "fr",
            "lat": 48.8617,
            "lng": 2.43484,
            "btn_text": "En savoir plus",
            "btn_url": "https:\/\/iledefrance.simplon.co\/je-candidate",
            "partner": null
        },
        {
            "factoryName": "Simplon Euskadi",
            "factoryId": 196,
            "regionId": 15,
            "regionName": "Nouvelle-Aquitaine",
            "countryId": 75,
            "countryName": "France",
            "address": "Bayonne",
            "city": null,
            "departement": "64",
            "postCode": "64100",
            "countryCode": "fr",
            "lat": 43.4925,
            "lng": -1.47629,
            "btn_text": "En savoir plus",
            "btn_url": "https:\/\/nouvelleaquitaine.simplon.co\/simplon-euskadi.html",
            "partner": null
        },
        {
            "factoryName": "Simplon Pau",
            "factoryId": 10,
            "regionId": 15,
            "regionName": "Nouvelle-Aquitaine",
            "countryId": 75,
            "countryName": "France",
            "address": "Pau",
            "city": null,
            "departement": "64",
            "postCode": "64000",
            "countryCode": "fr",
            "lat": 43.3008,
            "lng": -0.369863,
            "btn_text": "En savoir plus",
            "btn_url": "https:\/\/nouvelleaquitaine.simplon.co\/simplon-pau",
            "partner": "STEP SA"
        },
        {
            "factoryName": "Simplon Bordeaux",
            "factoryId": 13,
            "regionId": 15,
            "regionName": "Nouvelle-Aquitaine",
            "countryId": 75,
            "countryName": "France",
            "address": "Bordeaux",
            "city": null,
            "departement": "33",
            "postCode": "33000",
            "countryCode": "fr",
            "lat": 44.8378,
            "lng": -0.579512,
            "btn_text": "En savoir plus",
            "btn_url": "https:\/\/nouvelleaquitaine.simplon.co\/simplon-bordeaux.html",
            "partner": null
        },
        {
            "factoryName": "Simplon Narbonne",
            "factoryId": 43,
            "regionId": 16,
            "regionName": "Occitanie",
            "countryId": 75,
            "countryName": "France",
            "address": "Narbonne",
            "city": null,
            "departement": "11",
            "postCode": "11100",
            "countryCode": "fr",
            "lat": 43.1847,
            "lng": 3.00359,
            "btn_text": "En savoir plus",
            "btn_url": "https:\/\/occitanie.simplon.co\/",
            "partner": null
        },
        {
            "factoryName": "Simplon Toulouse",
            "factoryId": 4,
            "regionId": 16,
            "regionName": "Occitanie",
            "countryId": 75,
            "countryName": "France",
            "address": "Toulouse",
            "city": null,
            "departement": "31",
            "postCode": "31000",
            "countryCode": "fr",
            "lat": 43.6043,
            "lng": 1.44199,
            "btn_text": "En savoir plus",
            "btn_url": "https:\/\/occitanie.simplon.co\/",
            "partner": null
        },
        {
            "factoryName": "Simplon Narbonne",
            "factoryId": 206,
            "regionId": 16,
            "regionName": "Occitanie",
            "countryId": 75,
            "countryName": "France",
            "address": "30 Avenue Docteur Paul Pompidor",
            "city": "Narbonne",
            "departement": "11",
            "postCode": "11100",
            "countryCode": "fr",
            "lat": 43.1835,
            "lng": 2.97918,
            "btn_text": "",
            "btn_url": null,
            "partner": null
        },
        {
            "factoryName": "Simplon Al\u00e8s",
            "factoryId": 218,
            "regionId": 16,
            "regionName": "Occitanie",
            "countryId": 75,
            "countryName": "France",
            "address": "Al\u00e8s",
            "city": null,
            "departement": "30",
            "postCode": "30100",
            "countryCode": "fr",
            "lat": 44.1272,
            "lng": 4.08085,
            "btn_text": "",
            "btn_url": null,
            "partner": null
        },
        {
            "factoryName": "Simplon Bagnols-sur-C\u00e8ze",
            "factoryId": 175,
            "regionId": 16,
            "regionName": "Occitanie",
            "countryId": 75,
            "countryName": "France",
            "address": "188 Avenue du Commando Vigan Braquet",
            "city": "Bagnols-sur-C\u00e8ze",
            "departement": "30",
            "postCode": "30200",
            "countryCode": "fr",
            "lat": 44.1616,
            "lng": 4.61173,
            "btn_text": "",
            "btn_url": null,
            "partner": null
        },
        {
            "factoryName": "Simplon Saint-Gaudens",
            "factoryId": 56,
            "regionId": 16,
            "regionName": "Occitanie",
            "countryId": 75,
            "countryName": "France",
            "address": "Saint-Gaudens",
            "city": null,
            "departement": "31",
            "postCode": "31800",
            "countryCode": "fr",
            "lat": 43.1081,
            "lng": 0.723448,
            "btn_text": "En savoir plus",
            "btn_url": "https:\/\/occitanie.simplon.co\/",
            "partner": null
        },
        {
            "factoryName": "Simplon Lab\u00e8ge",
            "factoryId": 48,
            "regionId": 16,
            "regionName": "Occitanie",
            "countryId": 75,
            "countryName": "France",
            "address": "Lab\u00e8ge",
            "city": null,
            "departement": "31",
            "postCode": "31670",
            "countryCode": "fr",
            "lat": 43.5292,
            "lng": 1.53004,
            "btn_text": "En savoir plus",
            "btn_url": "https:\/\/occitanie.simplon.co\/",
            "partner": null
        },
        {
            "factoryName": "Simplon Cahors x Greta",
            "factoryId": 57,
            "regionId": 16,
            "regionName": "Occitanie",
            "countryId": 75,
            "countryName": "France",
            "address": "Cahors",
            "city": null,
            "departement": "46",
            "postCode": "46000",
            "countryCode": "fr",
            "lat": 44.4475,
            "lng": 1.44054,
            "btn_text": "En savoir plus",
            "btn_url": "https:\/\/occitanie.simplon.co\/",
            "partner": null
        },
        {
            "factoryName": "Simplon Carcassonne",
            "factoryId": 52,
            "regionId": 16,
            "regionName": "Occitanie",
            "countryId": 75,
            "countryName": "France",
            "address": "Carcassonne",
            "city": null,
            "departement": "11",
            "postCode": "11000",
            "countryCode": "fr",
            "lat": 43.2158,
            "lng": 2.35144,
            "btn_text": "En savoir plus",
            "btn_url": "https:\/\/occitanie.simplon.co\/",
            "partner": null
        },
        {
            "factoryName": "Simplon Castelnau-le-Lez",
            "factoryId": 55,
            "regionId": 16,
            "regionName": "Occitanie",
            "countryId": 75,
            "countryName": "France",
            "address": "Castelnau-le-Lez",
            "city": null,
            "departement": "34",
            "postCode": "34170",
            "countryCode": "fr",
            "lat": 43.6361,
            "lng": 3.90128,
            "btn_text": "En savoir plus",
            "btn_url": "https:\/\/occitanie.simplon.co\/",
            "partner": "Microsoft"
        },
        {
            "factoryName": "Simplon Auch",
            "factoryId": 51,
            "regionId": 16,
            "regionName": "Occitanie",
            "countryId": 75,
            "countryName": "France",
            "address": "Auch",
            "city": null,
            "departement": "32",
            "postCode": "32000",
            "countryCode": "fr",
            "lat": 43.6453,
            "lng": 0.588516,
            "btn_text": "En savoir plus",
            "btn_url": "https:\/\/occitanie.simplon.co\/",
            "partner": null
        },
        {
            "factoryName": "A distance",
            "factoryId": 42,
            "regionId": 16,
            "regionName": "Occitanie",
            "countryId": 75,
            "countryName": "France",
            "address": "Toulouse",
            "city": null,
            "departement": "31",
            "postCode": "31000",
            "countryCode": "fr",
            "lat": 43.6043,
            "lng": 1.44199,
            "btn_text": "En savoir plus",
            "btn_url": "https:\/\/occitanie.simplon.co\/",
            "partner": null
        },
        {
            "factoryName": "Simplon Carbonne",
            "factoryId": 39,
            "regionId": 16,
            "regionName": "Occitanie",
            "countryId": 75,
            "countryName": "France",
            "address": "Carbonne",
            "city": null,
            "departement": "31",
            "postCode": "31390",
            "countryCode": "fr",
            "lat": 43.2973,
            "lng": 1.21923,
            "btn_text": "En savoir plus",
            "btn_url": "https:\/\/occitanie.simplon.co\/",
            "partner": null
        },
        {
            "factoryName": "RSMA Guadeloupe - Baie-Mahault",
            "factoryId": 198,
            "regionId": 39,
            "regionName": "Outre-mer",
            "countryId": 75,
            "countryName": "France",
            "address": "Baie-Mahault",
            "city": null,
            "departement": "97",
            "postCode": "97122",
            "countryCode": "fr",
            "lat": 16.2675,
            "lng": -61.5868,
            "btn_text": "En savoir plus",
            "btn_url": "https:\/\/outremer.simplon.co\/",
            "partner": null
        },
        {
            "factoryName": "RSMA R\u00e9union - Saint-Pierre",
            "factoryId": 67,
            "regionId": 39,
            "regionName": "Outre-mer",
            "countryId": 75,
            "countryName": "France",
            "address": "Saint-Pierre",
            "city": null,
            "departement": "97",
            "postCode": "97410",
            "countryCode": "fr",
            "lat": -21.342,
            "lng": 55.4777,
            "btn_text": "En savoir plus",
            "btn_url": "https:\/\/outremer.simplon.co\/",
            "partner": null
        },
        {
            "factoryName": "RSMA Martinique -  Le Lamentin",
            "factoryId": 140,
            "regionId": 39,
            "regionName": "Outre-mer",
            "countryId": 75,
            "countryName": "France",
            "address": "Le Lamentin",
            "city": null,
            "departement": "97",
            "postCode": "97232",
            "countryCode": "mq",
            "lat": 14.6134,
            "lng": -60.9996,
            "btn_text": "En savoir plus",
            "btn_url": "https:\/\/outremer.simplon.co\/",
            "partner": null
        },
        {
            "factoryName": "CCI Nouvelle-Cal\u00e9donie - Noum\u00e9a",
            "factoryId": 81,
            "regionId": 39,
            "regionName": "Outre-mer",
            "countryId": 75,
            "countryName": "France",
            "address": "Noum\u00e9a",
            "city": null,
            "departement": "98",
            "postCode": "98800",
            "countryCode": "nc",
            "lat": -22.2741,
            "lng": 166.449,
            "btn_text": "En savoir plus",
            "btn_url": "https:\/\/outremer.simplon.co\/",
            "partner": null
        },
        {
            "factoryName": "Saint-Denis",
            "factoryId": 200,
            "regionId": 39,
            "regionName": "Outre-mer",
            "countryId": 75,
            "countryName": "France",
            "address": "Saint-Denis",
            "city": null,
            "departement": "97",
            "postCode": "97400",
            "countryCode": "fr",
            "lat": -20.879,
            "lng": 55.4481,
            "btn_text": "En savoir plus",
            "btn_url": "https:\/\/outremer.simplon.co\/",
            "partner": null
        },
        {
            "factoryName": "IRTS - Saint-Beno\u00eet",
            "factoryId": 195,
            "regionId": 39,
            "regionName": "Outre-mer",
            "countryId": 75,
            "countryName": "France",
            "address": "1 Rue Sully Brunet",
            "city": "Saint-Beno\u00eet",
            "departement": "97",
            "postCode": "97470",
            "countryCode": "fr",
            "lat": -21.0326,
            "lng": 55.7145,
            "btn_text": "En savoir plus",
            "btn_url": "https:\/\/outremer.simplon.co\/",
            "partner": null
        },
        {
            "factoryName": "Simplon Marseille R\u00e9publique",
            "factoryId": 114,
            "regionId": 18,
            "regionName": "Provence-Alpes-Cote d'Azur",
            "countryId": 75,
            "countryName": "France",
            "address": "50 Rue Fauchier",
            "city": "Marseille 2e Arrondissement",
            "departement": "13",
            "postCode": "13002",
            "countryCode": "fr",
            "lat": 43.3041,
            "lng": 5.3707,
            "btn_text": "En savoir plus",
            "btn_url": "https:\/\/paca.simplon.co\/",
            "partner": null
        },
        {
            "factoryName": "Simplon Cannes",
            "factoryId": 76,
            "regionId": 18,
            "regionName": "Provence-Alpes-Cote d'Azur",
            "countryId": 75,
            "countryName": "France",
            "address": "15 Avenue des Buissons Ardents",
            "city": "Cannes",
            "departement": "06",
            "postCode": "06150",
            "countryCode": "fr",
            "lat": 43.558,
            "lng": 6.96287,
            "btn_text": "En savoir plus",
            "btn_url": "https:\/\/paca.simplon.co\/",
            "partner": null
        },
        {
            "factoryName": "Avenir 84",
            "factoryId": 61,
            "regionId": 18,
            "regionName": "Provence-Alpes-Cote d'Azur",
            "countryId": 75,
            "countryName": "France",
            "address": "27 bis Avenue de la Trillade",
            "city": "Avignon",
            "departement": "84",
            "postCode": "84000",
            "countryCode": "fr",
            "lat": 43.9368,
            "lng": 4.82038,
            "btn_text": "En savoir plus",
            "btn_url": "https:\/\/paca.simplon.co\/",
            "partner": null
        },
        {
            "factoryName": "Simplon Marseille Le Clo\u00eetre",
            "factoryId": 15,
            "regionId": 18,
            "regionName": "Provence-Alpes-Cote d'Azur",
            "countryId": 75,
            "countryName": "France",
            "address": "20 Boulevard Madeleine Remusat",
            "city": "Marseille 13e Arrondissement",
            "departement": "13",
            "postCode": "13013",
            "countryCode": "fr",
            "lat": 43.3363,
            "lng": 5.4218,
            "btn_text": "En savoir plus",
            "btn_url": "https:\/\/paca.simplon.co\/",
            "partner": null
        },
        {
            "factoryName": "Simplon Nice",
            "factoryId": 72,
            "regionId": 18,
            "regionName": "Provence-Alpes-Cote d'Azur",
            "countryId": 75,
            "countryName": "France",
            "address": "61 Avenue Simone Veil",
            "city": "Nice",
            "departement": "06",
            "postCode": "06000",
            "countryCode": "fr",
            "lat": 43.6873,
            "lng": 7.20184,
            "btn_text": "En savoir plus",
            "btn_url": "https:\/\/paca.simplon.co\/",
            "partner": null
        },
        {
            "factoryName": "Simplon Berre l'Etang",
            "factoryId": 224,
            "regionId": 18,
            "regionName": "Provence-Alpes-Cote d'Azur",
            "countryId": 75,
            "countryName": "France",
            "address": "32 Boulevard Fr\u00e9d\u00e9ric Mistral",
            "city": "Berre-l'\u00c9tang",
            "departement": "13",
            "postCode": "13130",
            "countryCode": "fr",
            "lat": 43.4735,
            "lng": 5.16818,
            "btn_text": "",
            "btn_url": null,
            "partner": null
        },
        {
            "factoryName": "Ecole 241",
            "factoryId": 145,
            "regionId": 24,
            "regionName": "Libreville",
            "countryId": 80,
            "countryName": "Gabon",
            "address": "Gabon",
            "city": null,
            "departement": null,
            "postCode": null,
            "countryCode": "ga",
            "lat": -0.803689,
            "lng": 11.6094,
            "btn_text": "En savoir plus",
            "btn_url": "http:\/\/ecole241.org\/",
            "partner": "Ecole 241 - Simplon"
        },
        {
            "factoryName": "Orange Coding Academy",
            "factoryId": 99,
            "regionId": 35,
            "regionName": "Amman",
            "countryId": 114,
            "countryName": "Jordanie",
            "address": "Amman",
            "city": null,
            "departement": "11",
            "postCode": "11181",
            "countryCode": "jo",
            "lat": 31.9516,
            "lng": 35.924,
            "btn_text": "En savoir plus",
            "btn_url": "https:\/\/www.orange.jo",
            "partner": "Orange Jordan"
        },
        {
            "factoryName": "Chams NGO",
            "factoryId": 100,
            "regionId": 36,
            "regionName": "Mafraq",
            "countryId": 114,
            "countryName": "Jordanie",
            "address": "Marfaq",
            "city": null,
            "departement": null,
            "postCode": null,
            "countryCode": "jo",
            "lat": 32.3424,
            "lng": 36.2075,
            "btn_text": "En savoir plus",
            "btn_url": "https:\/\/www.chamsngo.org\/",
            "partner": null
        },
        {
            "factoryName": "Orange Digital Kalanso",
            "factoryId": 181,
            "regionId": 46,
            "regionName": "Bamako",
            "countryId": 134,
            "countryName": "Mali",
            "address": "Bamako",
            "city": null,
            "departement": "27",
            "postCode": "277",
            "countryCode": "ml",
            "lat": 12.6493,
            "lng": -8.00034,
            "btn_text": "En savoir plus",
            "btn_url": "https:\/\/international.simplon.co\/",
            "partner": null
        },
        {
            "factoryName": "Youcode Safi",
            "factoryId": 129,
            "regionId": 40,
            "regionName": "Safi",
            "countryId": 144,
            "countryName": "Maroc",
            "address": "Safi",
            "city": null,
            "departement": "46",
            "postCode": "46000",
            "countryCode": "ma",
            "lat": 32.2994,
            "lng": -9.23953,
            "btn_text": "En savoir plus",
            "btn_url": "https:\/\/maroc.simplon.co\/",
            "partner": "OCP"
        },
        {
            "factoryName": "Youcode",
            "factoryId": 97,
            "regionId": 19,
            "regionName": "Youssoufia",
            "countryId": 144,
            "countryName": "Maroc",
            "address": "Youssoufia",
            "city": null,
            "departement": null,
            "postCode": null,
            "countryCode": "ma",
            "lat": 32.2458,
            "lng": -8.53244,
            "btn_text": "En savoir plus",
            "btn_url": "https:\/\/youcode.ma\/",
            "partner": "OCP"
        },
        {
            "factoryName": "Simplon Maroc",
            "factoryId": 3,
            "regionId": 19,
            "regionName": "Youssoufia",
            "countryId": 144,
            "countryName": "Maroc",
            "address": "Youssoufia",
            "city": null,
            "departement": null,
            "postCode": null,
            "countryCode": "ma",
            "lat": 32.2458,
            "lng": -8.53244,
            "btn_text": "En savoir plus",
            "btn_url": "https:\/\/maroc.simplon.co\/",
            "partner": null
        },
        {
            "factoryName": "Kinshasa Digital",
            "factoryId": 179,
            "regionId": 44,
            "regionName": "Kinshasa Digital",
            "countryId": 52,
            "countryName": "R\u00e9publique D\u00e9mocratique du Congo",
            "address": "Kinshasa",
            "city": null,
            "departement": "10",
            "postCode": "1015",
            "countryCode": "cd",
            "lat": -4.32171,
            "lng": 15.3126,
            "btn_text": "En savoir plus",
            "btn_url": "https:\/\/republiquedemocratiqueducongo.simplon.co\/",
            "partner": null
        },
        {
            "factoryName": "Simplon Romania",
            "factoryId": 146,
            "regionId": 25,
            "regionName": "Cluj-Napoca",
            "countryId": 181,
            "countryName": "Roumanie",
            "address": "Strada G\u0103rii 21",
            "city": "Cluj-Napoca",
            "departement": "40",
            "postCode": "400265",
            "countryCode": "ro",
            "lat": 46.7873,
            "lng": 23.5926,
            "btn_text": "En savoir plus",
            "btn_url": "http:\/\/www.simplonromania.org\/",
            "partner": null
        },
        {
            "factoryName": "Sonatel Academy",
            "factoryId": 143,
            "regionId": 23,
            "regionName": "Dakar",
            "countryId": 193,
            "countryName": "S\u00e9n\u00e9gal",
            "address": "S\u00e9n\u00e9gal",
            "city": null,
            "departement": null,
            "postCode": null,
            "countryCode": "sn",
            "lat": 14.4974,
            "lng": -14.4524,
            "btn_text": "En savoir plus",
            "btn_url": "https:\/\/www.academysonatel.com\/",
            "partner": null
        },
        {
            "factoryName": "Simplon AUF Dakar",
            "factoryId": 86,
            "regionId": 23,
            "regionName": "Dakar",
            "countryId": 193,
            "countryName": "S\u00e9n\u00e9gal",
            "address": "Dakar",
            "city": null,
            "departement": "20",
            "postCode": "2084",
            "countryCode": "sn",
            "lat": 14.6934,
            "lng": -17.4479,
            "btn_text": "En savoir plus",
            "btn_url": "https:\/\/www.facebook.com\/fabriquesimplonaufdakar\/",
            "partner": "Agence universitaire de la Francophonie"
        },
        {
            "factoryName": "R\u00e9alise",
            "factoryId": 95,
            "regionId": 32,
            "regionName": "Gen\u00e8ve",
            "countryId": 210,
            "countryName": "Suisse",
            "address": "Gen\u00e8ve",
            "city": null,
            "departement": "12",
            "postCode": "1200",
            "countryCode": "ch",
            "lat": 46.2018,
            "lng": 6.1466,
            "btn_text": "En savoir plus",
            "btn_url": "https:\/\/www.realise.ch\/",
            "partner": null
        },
        {
            "factoryName": "Simplon Tunis",
            "factoryId": 98,
            "regionId": 34,
            "regionName": "Tunis",
            "countryId": 219,
            "countryName": "Tunisie",
            "address": "Tunis",
            "city": null,
            "departement": "10",
            "postCode": "1001",
            "countryCode": "tn",
            "lat": 36.8001,
            "lng": 10.1848,
            "btn_text": "En savoir plus",
            "btn_url": "https:\/\/www.facebook.com\/SimplonTunis\/",
            "partner": null
        }
    ],
    "factoriesAvailablesPlaces": [
        {
            "regionId": 29,
            "regionName": "Anvers",
            "countryId": 18,
            "countryName": "Belgique"
        },
        {
            "regionId": 26,
            "regionName": "Bruxelles",
            "countryId": 18,
            "countryName": "Belgique"
        },
        {
            "regionId": 28,
            "regionName": "Charleroi",
            "countryId": 18,
            "countryName": "Belgique"
        },
        {
            "regionId": 27,
            "regionName": "Genk, Vlaanderen",
            "countryId": 18,
            "countryName": "Belgique"
        },
        {
            "regionId": 30,
            "regionName": "Li\u00e8ge",
            "countryId": 18,
            "countryName": "Belgique"
        },
        {
            "regionId": 45,
            "regionName": "Ouagadougou",
            "countryId": 233,
            "countryName": "Burkina Faso"
        },
        {
            "regionId": 22,
            "regionName": "Abidjan",
            "countryId": 110,
            "countryName": "C\u00f4te d'Ivoire"
        },
        {
            "regionId": 31,
            "regionName": "Barcelone",
            "countryId": 203,
            "countryName": "Espagne"
        },
        {
            "regionId": 43,
            "regionName": "Bilbao",
            "countryId": 203,
            "countryName": "Espagne"
        },
        {
            "regionId": 42,
            "regionName": "Madrid",
            "countryId": 203,
            "countryName": "Espagne"
        },
        {
            "regionId": 1,
            "regionName": "Auvergne-Rh\u00f4ne-Alpes",
            "countryId": 75,
            "countryName": "France"
        },
        {
            "regionId": 3,
            "regionName": "Bourgogne-Franche-Comt\u00e9",
            "countryId": 75,
            "countryName": "France"
        },
        {
            "regionId": 4,
            "regionName": "Centre-Val de Loire",
            "countryId": 75,
            "countryName": "France"
        },
        {
            "regionId": 6,
            "regionName": "Grand Est",
            "countryId": 75,
            "countryName": "France"
        },
        {
            "regionId": 17,
            "regionName": "Grand Ouest",
            "countryId": 75,
            "countryName": "France"
        },
        {
            "regionId": 14,
            "regionName": "Haute-Normandie",
            "countryId": 75,
            "countryName": "France"
        },
        {
            "regionId": 9,
            "regionName": "Hauts-de-France",
            "countryId": 75,
            "countryName": "France"
        },
        {
            "regionId": 10,
            "regionName": "\u00cele-de-France",
            "countryId": 75,
            "countryName": "France"
        },
        {
            "regionId": 15,
            "regionName": "Nouvelle-Aquitaine",
            "countryId": 75,
            "countryName": "France"
        },
        {
            "regionId": 16,
            "regionName": "Occitanie",
            "countryId": 75,
            "countryName": "France"
        },
        {
            "regionId": 39,
            "regionName": "Outre-mer",
            "countryId": 75,
            "countryName": "France"
        },
        {
            "regionId": 18,
            "regionName": "Provence-Alpes-Cote d'Azur",
            "countryId": 75,
            "countryName": "France"
        },
        {
            "regionId": 24,
            "regionName": "Libreville",
            "countryId": 80,
            "countryName": "Gabon"
        },
        {
            "regionId": 35,
            "regionName": "Amman",
            "countryId": 114,
            "countryName": "Jordanie"
        },
        {
            "regionId": 36,
            "regionName": "Mafraq",
            "countryId": 114,
            "countryName": "Jordanie"
        },
        {
            "regionId": 46,
            "regionName": "Bamako",
            "countryId": 134,
            "countryName": "Mali"
        },
        {
            "regionId": 40,
            "regionName": "Safi",
            "countryId": 144,
            "countryName": "Maroc"
        },
        {
            "regionId": 19,
            "regionName": "Youssoufia",
            "countryId": 144,
            "countryName": "Maroc"
        },
        {
            "regionId": 44,
            "regionName": "Kinshasa Digital",
            "countryId": 52,
            "countryName": "R\u00e9publique D\u00e9mocratique du Congo"
        },
        {
            "regionId": 25,
            "regionName": "Cluj-Napoca",
            "countryId": 181,
            "countryName": "Roumanie"
        },
        {
            "regionId": 23,
            "regionName": "Dakar",
            "countryId": 193,
            "countryName": "S\u00e9n\u00e9gal"
        },
        {
            "regionId": 32,
            "regionName": "Gen\u00e8ve",
            "countryId": 210,
            "countryName": "Suisse"
        },
        {
            "regionId": 34,
            "regionName": "Tunis",
            "countryId": 219,
            "countryName": "Tunisie"
        }
    ]
}